[
  {
    "id": "e1",
    "source": "Agricultural and Biological Sciences",
    "target": "Business, Management and Accounting",
    "weight": 2.4,
    "stringsAsFactors": false
  },
  {
    "id": "e2",
    "source": "Agricultural and Biological Sciences",
    "target": "Computer Science",
    "weight": 0.4087,
    "stringsAsFactors": false
  },
  {
    "id": "e3",
    "source": "Agricultural and Biological Sciences",
    "target": "Decision Sciences",
    "weight": 1.6487,
    "stringsAsFactors": false
  },
  {
    "id": "e4",
    "source": "Agricultural and Biological Sciences",
    "target": "Economics, Econometrics and Finance",
    "weight": 0.944,
    "stringsAsFactors": false
  },
  {
    "id": "e5",
    "source": "Agricultural and Biological Sciences",
    "target": "Engineering",
    "weight": 1.8885,
    "stringsAsFactors": false
  },
  {
    "id": "e6",
    "source": "Agricultural and Biological Sciences",
    "target": "Environmental Science",
    "weight": 0.3635,
    "stringsAsFactors": false
  },
  {
    "id": "e7",
    "source": "Agricultural and Biological Sciences",
    "target": "Health Professions",
    "weight": 0.061,
    "stringsAsFactors": false
  },
  {
    "id": "e8",
    "source": "Agricultural and Biological Sciences",
    "target": "Mathematics",
    "weight": 0.2465,
    "stringsAsFactors": false
  },
  {
    "id": "e9",
    "source": "Agricultural and Biological Sciences",
    "target": "Medicine",
    "weight": 0.133,
    "stringsAsFactors": false
  },
  {
    "id": "e10",
    "source": "Agricultural and Biological Sciences",
    "target": "Physics and Astronomy",
    "weight": 0.4861,
    "stringsAsFactors": false
  },
  {
    "id": "e11",
    "source": "Agricultural and Biological Sciences",
    "target": "Psychology",
    "weight": 0.1183,
    "stringsAsFactors": false
  },
  {
    "id": "e12",
    "source": "Agricultural and Biological Sciences",
    "target": "Social Sciences",
    "weight": 6.5203,
    "stringsAsFactors": false
  },
  {
    "id": "e13",
    "source": "Arts and Humanities",
    "target": "Biochemistry, Genetics and Molecular Biology",
    "weight": 0.2214,
    "stringsAsFactors": false
  },
  {
    "id": "e14",
    "source": "Arts and Humanities",
    "target": "Business, Management and Accounting",
    "weight": 0.2822,
    "stringsAsFactors": false
  },
  {
    "id": "e15",
    "source": "Arts and Humanities",
    "target": "Computer Science",
    "weight": 0.1801,
    "stringsAsFactors": false
  },
  {
    "id": "e16",
    "source": "Arts and Humanities",
    "target": "Decision Sciences",
    "weight": 2.0886,
    "stringsAsFactors": false
  },
  {
    "id": "e17",
    "source": "Arts and Humanities",
    "target": "Economics, Econometrics and Finance",
    "weight": 0.081,
    "stringsAsFactors": false
  },
  {
    "id": "e18",
    "source": "Arts and Humanities",
    "target": "Engineering",
    "weight": 0.1777,
    "stringsAsFactors": false
  },
  {
    "id": "e19",
    "source": "Arts and Humanities",
    "target": "Environmental Science",
    "weight": 0.0502,
    "stringsAsFactors": false
  },
  {
    "id": "e20",
    "source": "Arts and Humanities",
    "target": "Materials Science",
    "weight": 0.1328,
    "stringsAsFactors": false
  },
  {
    "id": "e21",
    "source": "Arts and Humanities",
    "target": "Mathematics",
    "weight": 0.1712,
    "stringsAsFactors": false
  },
  {
    "id": "e22",
    "source": "Arts and Humanities",
    "target": "Medicine",
    "weight": 0.1007,
    "stringsAsFactors": false
  },
  {
    "id": "e23",
    "source": "Arts and Humanities",
    "target": "Physics and Astronomy",
    "weight": 0.4199,
    "stringsAsFactors": false
  },
  {
    "id": "e24",
    "source": "Arts and Humanities",
    "target": "Social Sciences",
    "weight": 3.348,
    "stringsAsFactors": false
  },
  {
    "id": "e25",
    "source": "Biochemistry, Genetics and Molecular Biology",
    "target": "Business, Management and Accounting",
    "weight": 1.5054,
    "stringsAsFactors": false
  },
  {
    "id": "e26",
    "source": "Biochemistry, Genetics and Molecular Biology",
    "target": "Computer Science",
    "weight": 1.7003,
    "stringsAsFactors": false
  },
  {
    "id": "e27",
    "source": "Biochemistry, Genetics and Molecular Biology",
    "target": "Decision Sciences",
    "weight": 5.0609,
    "stringsAsFactors": false
  },
  {
    "id": "e28",
    "source": "Biochemistry, Genetics and Molecular Biology",
    "target": "Economics, Econometrics and Finance",
    "weight": 1.1587,
    "stringsAsFactors": false
  },
  {
    "id": "e29",
    "source": "Biochemistry, Genetics and Molecular Biology",
    "target": "Energy",
    "weight": 0.1341,
    "stringsAsFactors": false
  },
  {
    "id": "e30",
    "source": "Biochemistry, Genetics and Molecular Biology",
    "target": "Engineering",
    "weight": 3.6948,
    "stringsAsFactors": false
  },
  {
    "id": "e31",
    "source": "Biochemistry, Genetics and Molecular Biology",
    "target": "Environmental Science",
    "weight": 0.1146,
    "stringsAsFactors": false
  },
  {
    "id": "e32",
    "source": "Biochemistry, Genetics and Molecular Biology",
    "target": "Mathematics",
    "weight": 1.7791,
    "stringsAsFactors": false
  },
  {
    "id": "e33",
    "source": "Biochemistry, Genetics and Molecular Biology",
    "target": "Medicine",
    "weight": 1.5612,
    "stringsAsFactors": false
  },
  {
    "id": "e34",
    "source": "Biochemistry, Genetics and Molecular Biology",
    "target": "Physics and Astronomy",
    "weight": 2.1847,
    "stringsAsFactors": false
  },
  {
    "id": "e35",
    "source": "Biochemistry, Genetics and Molecular Biology",
    "target": "Social Sciences",
    "weight": 29.9046,
    "stringsAsFactors": false
  },
  {
    "id": "e36",
    "source": "Business, Management and Accounting",
    "target": "Computer Science",
    "weight": 17.7445,
    "stringsAsFactors": false
  },
  {
    "id": "e37",
    "source": "Business, Management and Accounting",
    "target": "Decision Sciences",
    "weight": 34.8731,
    "stringsAsFactors": false
  },
  {
    "id": "e38",
    "source": "Business, Management and Accounting",
    "target": "Earth and Planetary Sciences",
    "weight": 0.75,
    "stringsAsFactors": false
  },
  {
    "id": "e39",
    "source": "Business, Management and Accounting",
    "target": "Economics, Econometrics and Finance",
    "weight": 20.78,
    "stringsAsFactors": false
  },
  {
    "id": "e40",
    "source": "Business, Management and Accounting",
    "target": "Energy",
    "weight": 6.7067,
    "stringsAsFactors": false
  },
  {
    "id": "e41",
    "source": "Business, Management and Accounting",
    "target": "Engineering",
    "weight": 36.6508,
    "stringsAsFactors": false
  },
  {
    "id": "e42",
    "source": "Business, Management and Accounting",
    "target": "Environmental Science",
    "weight": 8.3524,
    "stringsAsFactors": false
  },
  {
    "id": "e43",
    "source": "Business, Management and Accounting",
    "target": "Health Professions",
    "weight": 1.2349,
    "stringsAsFactors": false
  },
  {
    "id": "e44",
    "source": "Business, Management and Accounting",
    "target": "Immunology and Microbiology",
    "weight": 0.2255,
    "stringsAsFactors": false
  },
  {
    "id": "e45",
    "source": "Business, Management and Accounting",
    "target": "Materials Science",
    "weight": 0.5167,
    "stringsAsFactors": false
  },
  {
    "id": "e46",
    "source": "Business, Management and Accounting",
    "target": "Mathematics",
    "weight": 2.8892,
    "stringsAsFactors": false
  },
  {
    "id": "e47",
    "source": "Business, Management and Accounting",
    "target": "Medicine",
    "weight": 1.2089,
    "stringsAsFactors": false
  },
  {
    "id": "e48",
    "source": "Business, Management and Accounting",
    "target": "Physics and Astronomy",
    "weight": 6.8437,
    "stringsAsFactors": false
  },
  {
    "id": "e49",
    "source": "Business, Management and Accounting",
    "target": "Psychology",
    "weight": 0.2535,
    "stringsAsFactors": false
  },
  {
    "id": "e50",
    "source": "Business, Management and Accounting",
    "target": "Social Sciences",
    "weight": 52.9095,
    "stringsAsFactors": false
  },
  {
    "id": "e51",
    "source": "Computer Science",
    "target": "Decision Sciences",
    "weight": 114.3289,
    "stringsAsFactors": false
  },
  {
    "id": "e52",
    "source": "Computer Science",
    "target": "Economics, Econometrics and Finance",
    "weight": 26.1269,
    "stringsAsFactors": false
  },
  {
    "id": "e53",
    "source": "Computer Science",
    "target": "Energy",
    "weight": 0.6232,
    "stringsAsFactors": false
  },
  {
    "id": "e54",
    "source": "Computer Science",
    "target": "Engineering",
    "weight": 227.404,
    "stringsAsFactors": false
  },
  {
    "id": "e55",
    "source": "Computer Science",
    "target": "Environmental Science",
    "weight": 1.7756,
    "stringsAsFactors": false
  },
  {
    "id": "e56",
    "source": "Computer Science",
    "target": "Mathematics",
    "weight": 2.872,
    "stringsAsFactors": false
  },
  {
    "id": "e57",
    "source": "Computer Science",
    "target": "Medicine",
    "weight": 30.515,
    "stringsAsFactors": false
  },
  {
    "id": "e58",
    "source": "Computer Science",
    "target": "Neuroscience",
    "weight": 0.6604,
    "stringsAsFactors": false
  },
  {
    "id": "e59",
    "source": "Computer Science",
    "target": "Physics and Astronomy",
    "weight": 35.7943,
    "stringsAsFactors": false
  },
  {
    "id": "e60",
    "source": "Computer Science",
    "target": "Psychology",
    "weight": 2.0751,
    "stringsAsFactors": false
  },
  {
    "id": "e61",
    "source": "Computer Science",
    "target": "Social Sciences",
    "weight": 70.2649,
    "stringsAsFactors": false
  },
  {
    "id": "e62",
    "source": "Decision Sciences",
    "target": "Earth and Planetary Sciences",
    "weight": 0.7423,
    "stringsAsFactors": false
  },
  {
    "id": "e63",
    "source": "Decision Sciences",
    "target": "Economics, Econometrics and Finance",
    "weight": 53.8729,
    "stringsAsFactors": false
  },
  {
    "id": "e64",
    "source": "Decision Sciences",
    "target": "Energy",
    "weight": 1.4163,
    "stringsAsFactors": false
  },
  {
    "id": "e65",
    "source": "Decision Sciences",
    "target": "Engineering",
    "weight": 98.8276,
    "stringsAsFactors": false
  },
  {
    "id": "e66",
    "source": "Decision Sciences",
    "target": "Environmental Science",
    "weight": 4.2346,
    "stringsAsFactors": false
  },
  {
    "id": "e67",
    "source": "Decision Sciences",
    "target": "Health Professions",
    "weight": 0.8411,
    "stringsAsFactors": false
  },
  {
    "id": "e68",
    "source": "Decision Sciences",
    "target": "Materials Science",
    "weight": 0.6308,
    "stringsAsFactors": false
  },
  {
    "id": "e69",
    "source": "Decision Sciences",
    "target": "Mathematics",
    "weight": 10.4298,
    "stringsAsFactors": false
  },
  {
    "id": "e70",
    "source": "Decision Sciences",
    "target": "Medicine",
    "weight": 8.8372,
    "stringsAsFactors": false
  },
  {
    "id": "e71",
    "source": "Decision Sciences",
    "target": "Neuroscience",
    "weight": 0.1656,
    "stringsAsFactors": false
  },
  {
    "id": "e72",
    "source": "Decision Sciences",
    "target": "Physics and Astronomy",
    "weight": 22.2634,
    "stringsAsFactors": false
  },
  {
    "id": "e73",
    "source": "Decision Sciences",
    "target": "Psychology",
    "weight": 1.0754,
    "stringsAsFactors": false
  },
  {
    "id": "e74",
    "source": "Decision Sciences",
    "target": "Social Sciences",
    "weight": 167.667,
    "stringsAsFactors": false
  },
  {
    "id": "e75",
    "source": "Economics, Econometrics and Finance",
    "target": "Energy",
    "weight": 2.6269,
    "stringsAsFactors": false
  },
  {
    "id": "e76",
    "source": "Economics, Econometrics and Finance",
    "target": "Engineering",
    "weight": 27.4239,
    "stringsAsFactors": false
  },
  {
    "id": "e77",
    "source": "Economics, Econometrics and Finance",
    "target": "Environmental Science",
    "weight": 5.0025,
    "stringsAsFactors": false
  },
  {
    "id": "e78",
    "source": "Economics, Econometrics and Finance",
    "target": "Health Professions",
    "weight": 0.2955,
    "stringsAsFactors": false
  },
  {
    "id": "e79",
    "source": "Economics, Econometrics and Finance",
    "target": "Mathematics",
    "weight": 4.9637,
    "stringsAsFactors": false
  },
  {
    "id": "e80",
    "source": "Economics, Econometrics and Finance",
    "target": "Medicine",
    "weight": 1.6047,
    "stringsAsFactors": false
  },
  {
    "id": "e81",
    "source": "Economics, Econometrics and Finance",
    "target": "Neuroscience",
    "weight": 0.0667,
    "stringsAsFactors": false
  },
  {
    "id": "e82",
    "source": "Economics, Econometrics and Finance",
    "target": "Physics and Astronomy",
    "weight": 7.4639,
    "stringsAsFactors": false
  },
  {
    "id": "e83",
    "source": "Economics, Econometrics and Finance",
    "target": "Psychology",
    "weight": 0.2221,
    "stringsAsFactors": false
  },
  {
    "id": "e84",
    "source": "Economics, Econometrics and Finance",
    "target": "Social Sciences",
    "weight": 36.0134,
    "stringsAsFactors": false
  },
  {
    "id": "e85",
    "source": "Energy",
    "target": "Engineering",
    "weight": 5.7275,
    "stringsAsFactors": false
  },
  {
    "id": "e86",
    "source": "Energy",
    "target": "Environmental Science",
    "weight": 0.7386,
    "stringsAsFactors": false
  },
  {
    "id": "e87",
    "source": "Energy",
    "target": "Immunology and Microbiology",
    "weight": 0.0831,
    "stringsAsFactors": false
  },
  {
    "id": "e88",
    "source": "Energy",
    "target": "Mathematics",
    "weight": 0.2828,
    "stringsAsFactors": false
  },
  {
    "id": "e89",
    "source": "Energy",
    "target": "Medicine",
    "weight": 0.0781,
    "stringsAsFactors": false
  },
  {
    "id": "e90",
    "source": "Energy",
    "target": "Physics and Astronomy",
    "weight": 0.5399,
    "stringsAsFactors": false
  },
  {
    "id": "e91",
    "source": "Energy",
    "target": "Social Sciences",
    "weight": 1.2027,
    "stringsAsFactors": false
  },
  {
    "id": "e92",
    "source": "Engineering",
    "target": "Environmental Science",
    "weight": 6.5204,
    "stringsAsFactors": false
  },
  {
    "id": "e93",
    "source": "Engineering",
    "target": "Health Professions",
    "weight": 1.5853,
    "stringsAsFactors": false
  },
  {
    "id": "e94",
    "source": "Engineering",
    "target": "Immunology and Microbiology",
    "weight": 0.069,
    "stringsAsFactors": false
  },
  {
    "id": "e95",
    "source": "Engineering",
    "target": "Mathematics",
    "weight": 6.2212,
    "stringsAsFactors": false
  },
  {
    "id": "e96",
    "source": "Engineering",
    "target": "Medicine",
    "weight": 14.1465,
    "stringsAsFactors": false
  },
  {
    "id": "e97",
    "source": "Engineering",
    "target": "Neuroscience",
    "weight": 0.7159,
    "stringsAsFactors": false
  },
  {
    "id": "e98",
    "source": "Engineering",
    "target": "Physics and Astronomy",
    "weight": 22.5111,
    "stringsAsFactors": false
  },
  {
    "id": "e99",
    "source": "Engineering",
    "target": "Psychology",
    "weight": 1.0391,
    "stringsAsFactors": false
  },
  {
    "id": "e100",
    "source": "Engineering",
    "target": "Social Sciences",
    "weight": 76.9531,
    "stringsAsFactors": false
  },
  {
    "id": "e101",
    "source": "Environmental Science",
    "target": "Health Professions",
    "weight": 0.2541,
    "stringsAsFactors": false
  },
  {
    "id": "e102",
    "source": "Environmental Science",
    "target": "Mathematics",
    "weight": 0.4753,
    "stringsAsFactors": false
  },
  {
    "id": "e103",
    "source": "Environmental Science",
    "target": "Medicine",
    "weight": 0.0599,
    "stringsAsFactors": false
  },
  {
    "id": "e104",
    "source": "Environmental Science",
    "target": "Physics and Astronomy",
    "weight": 0.8754,
    "stringsAsFactors": false
  },
  {
    "id": "e105",
    "source": "Environmental Science",
    "target": "Social Sciences",
    "weight": 7.5281,
    "stringsAsFactors": false
  },
  {
    "id": "e106",
    "source": "Health Professions",
    "target": "Physics and Astronomy",
    "weight": 0.1662,
    "stringsAsFactors": false
  },
  {
    "id": "e107",
    "source": "Health Professions",
    "target": "Social Sciences",
    "weight": 2.0342,
    "stringsAsFactors": false
  },
  {
    "id": "e108",
    "source": "Immunology and Microbiology",
    "target": "Mathematics",
    "weight": 0.3651,
    "stringsAsFactors": false
  },
  {
    "id": "e109",
    "source": "Immunology and Microbiology",
    "target": "Social Sciences",
    "weight": 0.1095,
    "stringsAsFactors": false
  },
  {
    "id": "e110",
    "source": "Materials Science",
    "target": "Social Sciences",
    "weight": 0.3076,
    "stringsAsFactors": false
  },
  {
    "id": "e111",
    "source": "Mathematics",
    "target": "Medicine",
    "weight": 1.9062,
    "stringsAsFactors": false
  },
  {
    "id": "e112",
    "source": "Mathematics",
    "target": "Neuroscience",
    "weight": 0.0716,
    "stringsAsFactors": false
  },
  {
    "id": "e113",
    "source": "Mathematics",
    "target": "Physics and Astronomy",
    "weight": 2.6,
    "stringsAsFactors": false
  },
  {
    "id": "e114",
    "source": "Mathematics",
    "target": "Psychology",
    "weight": 0.0463,
    "stringsAsFactors": false
  },
  {
    "id": "e115",
    "source": "Mathematics",
    "target": "Social Sciences",
    "weight": 21.7962,
    "stringsAsFactors": false
  },
  {
    "id": "e116",
    "source": "Medicine",
    "target": "Physics and Astronomy",
    "weight": 1.1771,
    "stringsAsFactors": false
  },
  {
    "id": "e117",
    "source": "Medicine",
    "target": "Psychology",
    "weight": 0.1259,
    "stringsAsFactors": false
  },
  {
    "id": "e118",
    "source": "Medicine",
    "target": "Social Sciences",
    "weight": 15.7832,
    "stringsAsFactors": false
  },
  {
    "id": "e119",
    "source": "Neuroscience",
    "target": "Physics and Astronomy",
    "weight": 0.1513,
    "stringsAsFactors": false
  },
  {
    "id": "e120",
    "source": "Neuroscience",
    "target": "Psychology",
    "weight": 0.2449,
    "stringsAsFactors": false
  },
  {
    "id": "e121",
    "source": "Neuroscience",
    "target": "Social Sciences",
    "weight": 5.3066,
    "stringsAsFactors": false
  },
  {
    "id": "e122",
    "source": "Physics and Astronomy",
    "target": "Psychology",
    "weight": 0.4875,
    "stringsAsFactors": false
  },
  {
    "id": "e123",
    "source": "Physics and Astronomy",
    "target": "Social Sciences",
    "weight": 76.6986,
    "stringsAsFactors": false
  },
  {
    "id": "e124",
    "source": "Psychology",
    "target": "Social Sciences",
    "weight": 5.2858,
    "stringsAsFactors": false
  }
]
